pyrwgps/__init__.py
pyrwgps/apiclient.py
pyrwgps/py.typed
pyrwgps/ratelimiter.py
pyrwgps/ridewithgps.py
pyrwgps-0.0.6.dist-info/METADATA
pyrwgps-0.0.6.dist-info/WHEEL
pyrwgps-0.0.6.dist-info/licenses/LICENSE.txt
pyrwgps-0.0.6.dist-info/RECORD
