Metadata-Version: 2.4
Name: pyrwgps
Version: 0.0.6
Summary: A Python client for the RideWithGPS API. Not affiliated with RideWithGPS.
Project-URL: Homepage, https://github.com/ckdake/pyrwgps
Project-URL: Issues, https://github.com/ckdake/pyrwgps/issues
Project-URL: PyPI, https://pypi.org/project/pyrwgps/
Author-email: Chris Kelly <ckdake@ckdake.com>
License-Expression: MIT
License-File: LICENSE.txt
Classifier: License :: OSI Approved :: MIT License
Classifier: Operating System :: OS Independent
Classifier: Programming Language :: Python :: 3
Requires-Python: >=3.9
Requires-Dist: certifi>=2025.4.26
Requires-Dist: urllib3>=1.26.19
Provides-Extra: dev
Requires-Dist: black==25.1.0; extra == 'dev'
Requires-Dist: build==1.2.2.post1; extra == 'dev'
Requires-Dist: certifi==2025.7.14; extra == 'dev'
Requires-Dist: flake8==7.3.0; extra == 'dev'
Requires-Dist: mypy==1.17.0; extra == 'dev'
Requires-Dist: pylint==3.3.7; extra == 'dev'
Requires-Dist: pytest-cov==6.2.1; extra == 'dev'
Requires-Dist: pytest==8.4.1; extra == 'dev'
Requires-Dist: pyyaml==6.0.2; extra == 'dev'
Requires-Dist: twine==6.1.0; extra == 'dev'
Requires-Dist: urllib3==2.5.0; extra == 'dev'
Requires-Dist: vcrpy==7.0.0; extra == 'dev'
